LICENSE.txt
MANIFEST.in
runner
setup.cfg
setup.py
pywithmodule/__init__.py
pywithmodule/manage.py
pywithmodule/module.py
pywithmodule.egg-info/PKG-INFO
pywithmodule.egg-info/SOURCES.txt
pywithmodule.egg-info/dependency_links.txt
pywithmodule.egg-info/requires.txt
pywithmodule.egg-info/top_level.txt
pywithmodule/Blog/__init__.py
pywithmodule/Blog/admin.py
pywithmodule/Blog/forms.py
pywithmodule/Blog/models.py
pywithmodule/Blog/tests.py
pywithmodule/Blog/urls.py
pywithmodule/Blog/views.py
pywithmodule/Template/authorlist.html
pywithmodule/Template/base.html
pywithmodule/Template/book_list.html
pywithmodule/Template/contact_form.html
pywithmodule/Template/index.html
pywithmodule/Template/input.html
pywithmodule/Template/print.html
pywithmodule/Template/search_form.html
pywithmodule/Template/search_form2.html
pywithmodule/Template/search_results.html
pywithmodule/Template/searchbform.html
pywithmodule/Template/searchblog.html
pywithmodule/Template/template.html
pywithmodule/Template/template2.html
pywithmodule/static/css/bootstrap-responsive.css
pywithmodule/static/css/bootstrap.css
pywithmodule/static/css/style.css
pywithmodule/static/images/n.jpg
pywithmodule/static/images/search.png
pywithmodule/static/js/jquery.js