Metadata-Version: 1.0
Name: pywithmodule
Version: 1.4
Summary: dja App
Home-page: https://github.com/kocicjelena/py/
Author: Jelena
Author-email: kocicjelena@gmail.com
License: UNKNOWN
Platform: UNKNOWN
